logiri/__init__.py
logiri/logger_factory.py
logiri/py.typed
logiri-0.0.2.dist-info/METADATA
logiri-0.0.2.dist-info/WHEEL
logiri-0.0.2.dist-info/top_level.txt
logiri-0.0.2.dist-info/RECORD
