Metadata-Version: 2.1
Name: logiri
Version: 0.0.2
Summary: Package for logging
Author: Vladimir Vojtenko
Author-email: vladimirdev635@gmail.com
License: MIT
